dbl_us_to/__init__.py
dbl_us_to/client.py
dbl_us_to/http.py
dbl_us_to/model.py
dbl_us_to-1.0.0.dist-info/LICENSE
dbl_us_to-1.0.0.dist-info/METADATA
dbl_us_to-1.0.0.dist-info/WHEEL
dbl_us_to-1.0.0.dist-info/top_level.txt
dbl_us_to-1.0.0.dist-info/RECORD
