Metadata-Version: 2.1
Name: dbl-us-to
Version: 1.0.0
Summary: An API wrapper for discordbotslist.us.to written in Python
Home-page: https://github.com/MrSpinne/DiscordBotsList.py
Author: MrSpinne
Author-email: spinningplays.gaming@gmail.com
License: UNKNOWN
Keywords: discordbotslist,api,wrapper,botlist,stats,discord.py
Platform: UNKNOWN
Classifier: Programming Language :: Python :: 3
Classifier: License :: OSI Approved :: MIT License
Classifier: Operating System :: OS Independent
Requires-Python: >=3.7
Requires-Dist: discord.py
Requires-Dist: aiohttp
